dtool_utils/__init__.py
dtool_utils/derived_dataset.py
dtool_utils-0.1.0.dist-info/METADATA
dtool_utils-0.1.0.dist-info/WHEEL
dtool_utils-0.1.0.dist-info/top_level.txt
dtool_utils-0.1.0.dist-info/RECORD
